README
routrschema.py
setup.py
routr_schema.egg-info/PKG-INFO
routr_schema.egg-info/SOURCES.txt
routr_schema.egg-info/dependency_links.txt
routr_schema.egg-info/not-zip-safe
routr_schema.egg-info/requires.txt
routr_schema.egg-info/top_level.txt