Metadata-Version: 1.0
Name: routr-schema
Version: 0.1
Summary: Common guards for routr to validate request
Home-page: http://routr.readthedocs.org/
Author: Andrey Popp
Author-email: 8mayday@gmail.com
License: BSD
Platform: UNKNOWN
